awxclient/__init__.py
awxclient/base.py
awxclient/connection.py
awxclient/exception.py
awxclient-0.0.2.dist-info/LICENSE
awxclient-0.0.2.dist-info/METADATA
awxclient-0.0.2.dist-info/WHEEL
awxclient-0.0.2.dist-info/top_level.txt
awxclient-0.0.2.dist-info/RECORD
