Metadata-Version: 2.1
Name: awxclient
Version: 0.0.2
Summary: AWX python API client
Author-email: stana <author@example.com>
Project-URL: Homepage, https://github.com/stana/python-awxclient
Project-URL: Bug Tracker, https://github.com/stana/python-awxclient/issues
Classifier: Programming Language :: Python :: 3
Classifier: License :: OSI Approved :: Apache Software License
Classifier: Operating System :: OS Independent
Requires-Python: >=3.7
License-File: LICENSE
Requires-Dist: requests
